recipipe/__init__.py
recipipe/__main__.py
recipipe/_version.py
recipipe/core.py
recipipe/transformers.py
recipipe/utils.py
recipipe-0.1.dist-info/AUTHORS.md
recipipe-0.1.dist-info/LICENSE
recipipe-0.1.dist-info/METADATA
recipipe-0.1.dist-info/WHEEL
recipipe-0.1.dist-info/entry_points.txt
recipipe-0.1.dist-info/top_level.txt
recipipe-0.1.dist-info/RECORD
