Metadata-Version: 2.1
Name: recipipe
Version: 0.1
Summary: Improved pipelines for data science projects.
Home-page: UNKNOWN
Author: guiferviz
License: MIT, Copyright guiferviz
Keywords: datascience machinelearning pipeline sklearn pandas
Platform: UNKNOWN
Requires-Dist: pandas
Requires-Dist: scikit-learn
